FlyQuery-0.1.1.dist-info/DESCRIPTION.rst
FlyQuery-0.1.1.dist-info/METADATA
FlyQuery-0.1.1.dist-info/RECORD
FlyQuery-0.1.1.dist-info/WHEEL
FlyQuery-0.1.1.dist-info/metadata.json
FlyQuery-0.1.1.dist-info/top_level.txt
flyquery/flyquery.py
