Metadata-Version: 2.0
Name: FlyQuery
Version: 0.1.1
Summary: API for accessing FlyBase through url request and parsing out data
Home-page: https://pypi.python.org/pypi/flyquery
Author: Dennis Goldschmidt
Author-email: dennis.goldschmidt@neuro.fchampalimaud.org
License: GPLv3
Keywords: html scraping
Platform: Windows10Pro
Platform: MacOSX-ElCapitan
Classifier: Development Status :: 1 - Planning
Classifier: Operating System :: MacOS :: MacOS X
Classifier: Topic :: Utilities
Classifier: License :: OSI Approved :: GNU General Public License v3 (GPLv3)
Classifier: Programming Language :: Python :: 3.6
Requires-Python: >=3.6
